dokang_pdf/__init__.py
dokang_pdf/version.py
dokang_pdf-0.4.0.dist-info/LICENSE.txt
dokang_pdf-0.4.0.dist-info/METADATA
dokang_pdf-0.4.0.dist-info/WHEEL
dokang_pdf-0.4.0.dist-info/top_level.txt
dokang_pdf-0.4.0.dist-info/RECORD
