Metadata-Version: 2.1
Name: dokang-pdf
Version: 0.4.0
Summary: PDF harvester for Dokang
Home-page: UNKNOWN
Author: Polyconseil
Author-email: opensource+dokang@polyconseil.fr
License: UNKNOWN
Keywords: full-text search engine
Platform: UNKNOWN
Classifier: Development Status :: 3 - Alpha
Classifier: Environment :: Console
Classifier: License :: OSI Approved :: BSD License
Classifier: Programming Language :: Python
Classifier: Programming Language :: Python :: 3.7
Classifier: Programming Language :: Python :: 3.8
License-File: LICENSE.txt
Requires-Dist: dokang (>=0.7.0)
Requires-Dist: pdfminer3k (>=1.3.4)
